{
  "HUMAN": {
    "base": {
      "STRENGTH": 10,
      "CONSTITUTION": 10,
      "DEXTERITY": 10,
      "WILLPOWER": 10,
      "SPIRIT": 10,
      "MIND": 10
    },
    "multipliers": {
      "STRENGTH": 1.0,
      "CONSTITUTION": 1.0,
      "DEXTERITY": 1.0,
      "WILLPOWER": 1.0,
      "SPIRIT": 1.0,
      "MIND": 1.0
    }
  },
  "SAIYAN": {
    "base": {
      "STRENGTH": 14,
      "CONSTITUTION": 10,
      "DEXTERITY": 12,
      "WILLPOWER": 8,
      "SPIRIT": 6,
      "MIND": 10
    },
    "multipliers": {
      "STRENGTH": 1.3,
      "CONSTITUTION": 1.0,
      "DEXTERITY": 1.2,
      "WILLPOWER": 0.8,
      "SPIRIT": 0.7,
      "MIND": 1.0
    }
  },
  "NAMEKIAN": {
    "base": {
      "STRENGTH": 8,
      "CONSTITUTION": 8,
      "DEXTERITY": 10,
      "WILLPOWER": 11,
      "SPIRIT": 13,
      "MIND": 10
    },
    "multipliers": {
      "STRENGTH": 0.8,
      "CONSTITUTION": 0.9,
      "DEXTERITY": 0.9,
      "WILLPOWER": 1.1,
      "SPIRIT": 1.3,
      "MIND": 1.0
    }
  },
  "COLD DEMON": {
    "base": {
      "STRENGTH": 8,
      "CONSTITUTION": 8,
      "DEXTERITY": 10,
      "WILLPOWER": 12,
      "SPIRIT": 12,
      "MIND": 10
    },
    "multipliers": {
      "STRENGTH": 0.9,
      "CONSTITUTION": 0.9,
      "DEXTERITY": 1.0,
      "WILLPOWER": 1.2,
      "SPIRIT": 1.1,
      "MIND": 1.0
    }
  },
  "MAJIN": {
    "base": {
      "STRENGTH": 10,
      "CONSTITUTION": 8,
      "DEXTERITY": 14,
      "WILLPOWER": 8,
      "SPIRIT": 10,
      "MIND": 10
    },
    "multipliers": {
      "STRENGTH": 0.9,
      "CONSTITUTION": 1.3,
      "DEXTERITY": 0.9,
      "WILLPOWER": 1.1,
      "SPIRIT": 0.8,
      "MIND": 1.0
    }
  }
}